wykop/__init__.py
wykop/utils.py
wykop/api/__init__.py
wykop/api/api_const.py
wykop/api/api_values.py
wykop/api/client.py
wykop/api/multi_key_client.py
wykop/api/exceptions/__init__.py
wykop/api/exceptions/base.py
wykop/api/exceptions/client_exceptions.py
wykop/api/exceptions/resolvers.py
wykop/api/models/__init__.py
wykop/api/models/model_utils.py
wykop/api/models/models.py
wykop/api/models/wykop_connect.py
wykop/core/__init__.py
wykop/core/credentials.py
wykop/core/requestor.py
wykop/core/parsers/__init__.py
wykop/core/parsers/base.py
wykop/core/parsers/json.py
wykop/core/requesters/__init__.py
wykop/core/requesters/base.py
wykop/core/requesters/requests.py
wykop/core/requesters/urllib.py
wykop_sdk_reborn-0.9.4.dist-info/LICENSE.txt
wykop_sdk_reborn-0.9.4.dist-info/METADATA
wykop_sdk_reborn-0.9.4.dist-info/WHEEL
wykop_sdk_reborn-0.9.4.dist-info/top_level.txt
wykop_sdk_reborn-0.9.4.dist-info/RECORD
