Metadata-Version: 2.1
Name: wykop-sdk-reborn
Version: 0.9.4
Summary: Client library for Wykop API v2
Home-page: https://github.com/krasnoludkolo/wykop-sdk-reborn
Author: Jan Danecki
Author-email: janek@projmen.pl
License: MIT
Platform: UNKNOWN
Classifier: Programming Language :: Python :: 2.7
Classifier: Programming Language :: Python :: 3.3
Classifier: Programming Language :: Python :: 3.4
Classifier: Programming Language :: Python :: 3.5
Classifier: Programming Language :: Python :: 3.6
Classifier: License :: OSI Approved :: MIT License
Classifier: Programming Language :: Python
Classifier: Topic :: Software Development :: Libraries :: Python Modules
License-File: LICENSE.txt
Requires-Dist: six (==1.15.0)
